{
    "phase": {
        "entities": [
            {
                "aceleration": 7.0,
                "health": 0,
                "jumpClock": 2.402463436126709,
                "lastPositionClock": 0.8744568824768066,
                "lastPosition_x": 346.7910461425781,
                "lastPosition_y": 1048.0,
                "position_x": 440.0,
                "position_y": 768.0,
                "teleportClock": 4.9113945960998535,
                "type": "Saci"
            },
            {
                "aceleration": 7.0,
                "health": 5,
                "jumpClock": 38.04823303222656,
                "lastPositionClock": 0.739302933216095,
                "lastPosition_x": 4093.9228515625,
                "lastPosition_y": 1048.0,
                "position_x": 5884.0,
                "position_y": 768.0,
                "teleportClock": 38.04823303222656,
                "type": "Saci"
            },
            {
                "aceleration": 7.0,
                "health": 0,
                "jumpClock": 1.8475079536437988,
                "lastPositionClock": 0.4030349850654602,
                "lastPosition_x": 3813.720947265625,
                "lastPosition_y": 1048.0,
                "position_x": 3284.1865234375,
                "position_y": 768.0,
                "teleportClock": 4.349801540374756,
                "type": "Saci"
            },
            {
                "aceleration": 7.0,
                "health": 5,
                "jumpClock": 38.04823303222656,
                "lastPositionClock": 0.739302933216095,
                "lastPosition_x": 4093.9228515625,
                "lastPosition_y": 1048.0,
                "position_x": 6482.0,
                "position_y": 768.0,
                "teleportClock": 38.04823303222656,
                "type": "Saci"
            },
            {
                "aceleration": 4.0,
                "alive": true,
                "evilness": 7,
                "faced_right": 1,
                "health": 5,
                "position_x": 11647.90625,
                "position_y": 774.0,
                "potionClock": 0.25204601883888245,
                "strength": 2,
                "type": "Cuca"
            },
            {
                "aceleration": 4.0,
                "alive": true,
                "evilness": 7,
                "faced_right": 1,
                "health": 5,
                "position_x": 11699.9140625,
                "position_y": 774.0,
                "potionClock": 0.25204601883888245,
                "strength": 2,
                "type": "Cuca"
            },
            {
                "aceleration": 4.0,
                "alive": false,
                "evilness": 7,
                "faced_right": -1,
                "health": 0,
                "position_x": 2215.161376953125,
                "position_y": 774.0,
                "potionClock": 0.11771100014448166,
                "strength": 2,
                "type": "Cuca"
            },
            {
                "aceleration": 4.0,
                "alive": true,
                "evilness": 7,
                "faced_right": 1,
                "health": 5,
                "position_x": 7601.0,
                "position_y": 774.0,
                "potionClock": 0.25204601883888245,
                "strength": 2,
                "type": "Cuca"
            },
            {
                "aceleration": 4.0,
                "alive": false,
                "evilness": 7,
                "faced_right": -1,
                "health": 0,
                "position_x": 3760.33984375,
                "position_y": 774.0,
                "potionClock": 1.3763477802276611,
                "strength": 2,
                "type": "Cuca"
            },
            {
                "position_x": 150.0,
                "position_y": 824.0,
                "type": "Honey",
                "viscosity": 0.550000011920929
            },
            {
                "position_x": 200.0,
                "position_y": 824.0,
                "type": "Honey",
                "viscosity": 0.550000011920929
            },
            {
                "position_x": 8200.0,
                "position_y": 824.0,
                "type": "Honey",
                "viscosity": 0.550000011920929
            },
            {
                "position_x": 8250.0,
                "position_y": 824.0,
                "type": "Honey",
                "viscosity": 0.550000011920929
            },
            {
                "position_x": 3400.0,
                "position_y": 824.0,
                "type": "Honey",
                "viscosity": 0.550000011920929
            },
            {
                "position_x": 3450.0,
                "position_y": 824.0,
                "type": "Honey",
                "viscosity": 0.550000011920929
            },
            {
                "position_x": 2500.0,
                "position_y": 824.0,
                "type": "Honey",
                "viscosity": 0.550000011920929
            },
            {
                "position_x": 2550.0,
                "position_y": 824.0,
                "type": "Honey",
                "viscosity": 0.550000011920929
            },
            {
                "position_x": 8400.0,
                "position_y": 824.0,
                "type": "Honey",
                "viscosity": 0.550000011920929
            },
            {
                "position_x": 8450.0,
                "position_y": 824.0,
                "type": "Honey",
                "viscosity": 0.550000011920929
            },
            {
                "position_x": 11100.0,
                "position_y": 824.0,
                "type": "Honey",
                "viscosity": 0.550000011920929
            },
            {
                "position_x": 11150.0,
                "position_y": 824.0,
                "type": "Honey",
                "viscosity": 0.550000011920929
            },
            {
                "position_x": 2650.0,
                "position_y": 824.0,
                "type": "Honey",
                "viscosity": 0.550000011920929
            },
            {
                "position_x": 2700.0,
                "position_y": 824.0,
                "type": "Honey",
                "viscosity": 0.550000011920929
            },
            {
                "position_x": 5700.0,
                "position_y": 824.0,
                "type": "Honey",
                "viscosity": 0.550000011920929
            },
            {
                "position_x": 5750.0,
                "position_y": 824.0,
                "type": "Honey",
                "viscosity": 0.550000011920929
            },
            {
                "position_x": 11750.0,
                "position_y": 824.0,
                "type": "Honey",
                "viscosity": 0.550000011920929
            },
            {
                "position_x": 11800.0,
                "position_y": 824.0,
                "type": "Honey",
                "viscosity": 0.550000011920929
            },
            {
                "position_x": 2850.0,
                "position_y": 824.0,
                "type": "Honey",
                "viscosity": 0.550000011920929
            },
            {
                "position_x": 2900.0,
                "position_y": 824.0,
                "type": "Honey",
                "viscosity": 0.550000011920929
            },
            {
                "clock": 0.0,
                "isActive": false,
                "originalPosition_x": 8787.0,
                "originalPosition_y": 190.0,
                "plataformSize_x": 8787.0,
                "plataformSize_y": 190.0,
                "plataformType": 0,
                "position_x": 8787.0,
                "position_y": 190.0,
                "regenClock": 38.04823303222656,
                "size_x": 34.0,
                "size_y": 10.5,
                "type": "Plataform",
                "velocity_x": 0.0,
                "velocity_y": 0.0
            },
            {
                "clock": 0.0,
                "isActive": false,
                "originalPosition_x": 8844.7998046875,
                "originalPosition_y": 190.0,
                "plataformSize_x": 8844.7998046875,
                "plataformSize_y": 190.0,
                "plataformType": 0,
                "position_x": 8844.7998046875,
                "position_y": 190.0,
                "regenClock": 38.04823303222656,
                "size_x": 34.0,
                "size_y": 10.5,
                "type": "Plataform",
                "velocity_x": 0.0,
                "velocity_y": 0.0
            },
            {
                "clock": 0.0,
                "isActive": false,
                "originalPosition_x": 9455.0,
                "originalPosition_y": 223.0,
                "plataformSize_x": 9455.0,
                "plataformSize_y": 223.0,
                "plataformType": 1,
                "position_x": 9455.0,
                "position_y": 223.0,
                "regenClock": 38.04823303222656,
                "size_x": 26.5,
                "size_y": 11.5,
                "type": "Plataform",
                "velocity_x": 0.0,
                "velocity_y": 0.0
            },
            {
                "clock": 0.0,
                "isActive": false,
                "originalPosition_x": 9500.0498046875,
                "originalPosition_y": 223.0,
                "plataformSize_x": 9500.0498046875,
                "plataformSize_y": 223.0,
                "plataformType": 1,
                "position_x": 9500.0498046875,
                "position_y": 223.0,
                "regenClock": 38.04823303222656,
                "size_x": 26.5,
                "size_y": 11.5,
                "type": "Plataform",
                "velocity_x": 0.0,
                "velocity_y": 0.0
            },
            {
                "clock": 0.0,
                "isActive": false,
                "originalPosition_x": 5186.0,
                "originalPosition_y": 125.0,
                "plataformSize_x": 5186.0,
                "plataformSize_y": 125.0,
                "plataformType": 0,
                "position_x": 5186.0,
                "position_y": 125.0,
                "regenClock": 38.04823303222656,
                "size_x": 34.0,
                "size_y": 10.5,
                "type": "Plataform",
                "velocity_x": 0.0,
                "velocity_y": 0.0
            },
            {
                "clock": 0.0,
                "isActive": false,
                "originalPosition_x": 5243.7998046875,
                "originalPosition_y": 125.0,
                "plataformSize_x": 5243.7998046875,
                "plataformSize_y": 125.0,
                "plataformType": 0,
                "position_x": 5243.7998046875,
                "position_y": 125.0,
                "regenClock": 38.04823303222656,
                "size_x": 34.0,
                "size_y": 10.5,
                "type": "Plataform",
                "velocity_x": 0.0,
                "velocity_y": 0.0
            },
            {
                "clock": 0.0,
                "isActive": false,
                "originalPosition_x": 1238.0,
                "originalPosition_y": 252.0,
                "plataformSize_x": 1238.0,
                "plataformSize_y": 252.0,
                "plataformType": 1,
                "position_x": 1238.0,
                "position_y": 252.0,
                "regenClock": 38.04823303222656,
                "size_x": 26.5,
                "size_y": 11.5,
                "type": "Plataform",
                "velocity_x": 0.0,
                "velocity_y": 0.0
            },
            {
                "clock": 0.0,
                "isActive": false,
                "originalPosition_x": 1283.050048828125,
                "originalPosition_y": 252.0,
                "plataformSize_x": 1283.050048828125,
                "plataformSize_y": 252.0,
                "plataformType": 1,
                "position_x": 1283.050048828125,
                "position_y": 252.0,
                "regenClock": 38.04823303222656,
                "size_x": 26.5,
                "size_y": 11.5,
                "type": "Plataform",
                "velocity_x": 0.0,
                "velocity_y": 0.0
            },
            {
                "clock": 0.0,
                "isActive": false,
                "originalPosition_x": 2159.0,
                "originalPosition_y": 465.0,
                "plataformSize_x": 2159.0,
                "plataformSize_y": 465.0,
                "plataformType": 1,
                "position_x": 2159.0,
                "position_y": 465.0,
                "regenClock": 38.04823303222656,
                "size_x": 26.5,
                "size_y": 11.5,
                "type": "Plataform",
                "velocity_x": 0.0,
                "velocity_y": 0.0
            },
            {
                "clock": 0.0,
                "isActive": false,
                "originalPosition_x": 2204.050048828125,
                "originalPosition_y": 465.0,
                "plataformSize_x": 2204.050048828125,
                "plataformSize_y": 465.0,
                "plataformType": 1,
                "position_x": 2204.050048828125,
                "position_y": 465.0,
                "regenClock": 38.04823303222656,
                "size_x": 26.5,
                "size_y": 11.5,
                "type": "Plataform",
                "velocity_x": 0.0,
                "velocity_y": 0.0
            },
            {
                "clock": 0.0,
                "isActive": false,
                "originalPosition_x": 4597.0,
                "originalPosition_y": 641.0,
                "plataformSize_x": 4597.0,
                "plataformSize_y": 641.0,
                "plataformType": 0,
                "position_x": 4597.0,
                "position_y": 641.0,
                "regenClock": 38.04823303222656,
                "size_x": 34.0,
                "size_y": 10.5,
                "type": "Plataform",
                "velocity_x": 0.0,
                "velocity_y": 0.0
            },
            {
                "clock": 0.0,
                "isActive": false,
                "originalPosition_x": 4654.7998046875,
                "originalPosition_y": 641.0,
                "plataformSize_x": 4654.7998046875,
                "plataformSize_y": 641.0,
                "plataformType": 0,
                "position_x": 4654.7998046875,
                "position_y": 641.0,
                "regenClock": 38.04823303222656,
                "size_x": 34.0,
                "size_y": 10.5,
                "type": "Plataform",
                "velocity_x": 0.0,
                "velocity_y": 0.0
            },
            {
                "clock": 0.0,
                "isActive": false,
                "originalPosition_x": 840.0,
                "originalPosition_y": 524.0,
                "plataformSize_x": 840.0,
                "plataformSize_y": 524.0,
                "plataformType": 1,
                "position_x": 840.0,
                "position_y": 524.0,
                "regenClock": 38.04823303222656,
                "size_x": 26.5,
                "size_y": 11.5,
                "type": "Plataform",
                "velocity_x": 0.0,
                "velocity_y": 0.0
            },
            {
                "clock": 0.0,
                "isActive": false,
                "originalPosition_x": 885.0499877929688,
                "originalPosition_y": 524.0,
                "plataformSize_x": 885.0499877929688,
                "plataformSize_y": 524.0,
                "plataformType": 1,
                "position_x": 885.0499877929688,
                "position_y": 524.0,
                "regenClock": 38.04823303222656,
                "size_x": 26.5,
                "size_y": 11.5,
                "type": "Plataform",
                "velocity_x": 0.0,
                "velocity_y": 0.0
            },
            {
                "clock": 0.0,
                "isActive": false,
                "originalPosition_x": 4411.0,
                "originalPosition_y": 297.0,
                "plataformSize_x": 4411.0,
                "plataformSize_y": 297.0,
                "plataformType": 0,
                "position_x": 4411.0,
                "position_y": 297.0,
                "regenClock": 38.04823303222656,
                "size_x": 34.0,
                "size_y": 10.5,
                "type": "Plataform",
                "velocity_x": 0.0,
                "velocity_y": 0.0
            },
            {
                "clock": 0.0,
                "isActive": false,
                "originalPosition_x": 4468.7998046875,
                "originalPosition_y": 297.0,
                "plataformSize_x": 4468.7998046875,
                "plataformSize_y": 297.0,
                "plataformType": 0,
                "position_x": 4468.7998046875,
                "position_y": 297.0,
                "regenClock": 38.04823303222656,
                "size_x": 34.0,
                "size_y": 10.5,
                "type": "Plataform",
                "velocity_x": 0.0,
                "velocity_y": 0.0
            },
            {
                "clock": 0.0,
                "isActive": false,
                "originalPosition_x": 3805.0,
                "originalPosition_y": 265.0,
                "plataformSize_x": 3805.0,
                "plataformSize_y": 265.0,
                "plataformType": 0,
                "position_x": 3805.0,
                "position_y": 265.0,
                "regenClock": 38.04823303222656,
                "size_x": 34.0,
                "size_y": 10.5,
                "type": "Plataform",
                "velocity_x": 0.0,
                "velocity_y": 0.0
            },
            {
                "clock": 0.0,
                "isActive": false,
                "originalPosition_x": 3862.800048828125,
                "originalPosition_y": 265.0,
                "plataformSize_x": 3862.800048828125,
                "plataformSize_y": 265.0,
                "plataformType": 0,
                "position_x": 3862.800048828125,
                "position_y": 265.0,
                "regenClock": 38.04823303222656,
                "size_x": 34.0,
                "size_y": 10.5,
                "type": "Plataform",
                "velocity_x": 0.0,
                "velocity_y": 0.0
            },
            {
                "clock": 0.0,
                "isActive": false,
                "originalPosition_x": 1810.0,
                "originalPosition_y": 321.0,
                "plataformSize_x": 1810.0,
                "plataformSize_y": 321.0,
                "plataformType": 1,
                "position_x": 1810.0,
                "position_y": 321.0,
                "regenClock": 38.04823303222656,
                "size_x": 26.5,
                "size_y": 11.5,
                "type": "Plataform",
                "velocity_x": 0.0,
                "velocity_y": 0.0
            },
            {
                "clock": 0.0,
                "isActive": false,
                "originalPosition_x": 1855.050048828125,
                "originalPosition_y": 321.0,
                "plataformSize_x": 1855.050048828125,
                "plataformSize_y": 321.0,
                "plataformType": 1,
                "position_x": 1855.050048828125,
                "position_y": 321.0,
                "regenClock": 38.04823303222656,
                "size_x": 26.5,
                "size_y": 11.5,
                "type": "Plataform",
                "velocity_x": 0.0,
                "velocity_y": 0.0
            },
            {
                "clock": 0.0,
                "isActive": false,
                "originalPosition_x": 976.0,
                "originalPosition_y": 658.0,
                "plataformSize_x": 976.0,
                "plataformSize_y": 658.0,
                "plataformType": 1,
                "position_x": 976.0,
                "position_y": 658.0,
                "regenClock": 38.04823303222656,
                "size_x": 26.5,
                "size_y": 11.5,
                "type": "Plataform",
                "velocity_x": 0.0,
                "velocity_y": 0.0
            },
            {
                "clock": 0.0,
                "isActive": false,
                "originalPosition_x": 1021.0499877929688,
                "originalPosition_y": 658.0,
                "plataformSize_x": 1021.0499877929688,
                "plataformSize_y": 658.0,
                "plataformType": 1,
                "position_x": 1021.0499877929688,
                "position_y": 658.0,
                "regenClock": 38.04823303222656,
                "size_x": 26.500030517578125,
                "size_y": 11.5,
                "type": "Plataform",
                "velocity_x": 0.0,
                "velocity_y": 0.0
            },
            {
                "clock": 0.0,
                "isActive": false,
                "originalPosition_x": 5033.0,
                "originalPosition_y": 315.0,
                "plataformSize_x": 5033.0,
                "plataformSize_y": 315.0,
                "plataformType": 1,
                "position_x": 5033.0,
                "position_y": 315.0,
                "regenClock": 38.04823303222656,
                "size_x": 26.5,
                "size_y": 11.5,
                "type": "Plataform",
                "velocity_x": 0.0,
                "velocity_y": 0.0
            },
            {
                "clock": 0.0,
                "isActive": false,
                "originalPosition_x": 5078.0498046875,
                "originalPosition_y": 315.0,
                "plataformSize_x": 5078.0498046875,
                "plataformSize_y": 315.0,
                "plataformType": 1,
                "position_x": 5078.0498046875,
                "position_y": 315.0,
                "regenClock": 38.04823303222656,
                "size_x": 26.5,
                "size_y": 11.5,
                "type": "Plataform",
                "velocity_x": 0.0,
                "velocity_y": 0.0
            },
            {
                "clock": 0.0,
                "isActive": false,
                "originalPosition_x": 2703.0,
                "originalPosition_y": 552.0,
                "plataformSize_x": 2703.0,
                "plataformSize_y": 552.0,
                "plataformType": 0,
                "position_x": 2703.0,
                "position_y": 552.0,
                "regenClock": 38.04823303222656,
                "size_x": 34.0,
                "size_y": 10.5,
                "type": "Plataform",
                "velocity_x": 0.0,
                "velocity_y": 0.0
            },
            {
                "clock": 0.0,
                "isActive": false,
                "originalPosition_x": 2760.800048828125,
                "originalPosition_y": 552.0,
                "plataformSize_x": 2760.800048828125,
                "plataformSize_y": 552.0,
                "plataformType": 0,
                "position_x": 2760.800048828125,
                "position_y": 552.0,
                "regenClock": 38.04823303222656,
                "size_x": 34.0,
                "size_y": 10.5,
                "type": "Plataform",
                "velocity_x": 0.0,
                "velocity_y": 0.0
            },
            {
                "clock": 0.0,
                "isActive": false,
                "originalPosition_x": 9321.0,
                "originalPosition_y": 692.0,
                "plataformSize_x": 9321.0,
                "plataformSize_y": 692.0,
                "plataformType": 0,
                "position_x": 9321.0,
                "position_y": 692.0,
                "regenClock": 38.04823303222656,
                "size_x": 34.0,
                "size_y": 10.5,
                "type": "Plataform",
                "velocity_x": 0.0,
                "velocity_y": 0.0
            },
            {
                "clock": 0.0,
                "isActive": false,
                "originalPosition_x": 9378.7998046875,
                "originalPosition_y": 692.0,
                "plataformSize_x": 9378.7998046875,
                "plataformSize_y": 692.0,
                "plataformType": 0,
                "position_x": 9378.7998046875,
                "position_y": 692.0,
                "regenClock": 38.04823303222656,
                "size_x": 34.0,
                "size_y": 10.5,
                "type": "Plataform",
                "velocity_x": 0.0,
                "velocity_y": 0.0
            },
            {
                "clock": 0.0,
                "isActive": false,
                "originalPosition_x": 10172.0,
                "originalPosition_y": 353.0,
                "plataformSize_x": 10172.0,
                "plataformSize_y": 353.0,
                "plataformType": 0,
                "position_x": 10172.0,
                "position_y": 353.0,
                "regenClock": 38.04823303222656,
                "size_x": 34.0,
                "size_y": 10.5,
                "type": "Plataform",
                "velocity_x": 0.0,
                "velocity_y": 0.0
            },
            {
                "clock": 0.0,
                "isActive": false,
                "originalPosition_x": 10229.7998046875,
                "originalPosition_y": 353.0,
                "plataformSize_x": 10229.7998046875,
                "plataformSize_y": 353.0,
                "plataformType": 0,
                "position_x": 10229.7998046875,
                "position_y": 353.0,
                "regenClock": 38.04823303222656,
                "size_x": 34.0,
                "size_y": 10.5,
                "type": "Plataform",
                "velocity_x": 0.0,
                "velocity_y": 0.0
            },
            {
                "clock": 0.0,
                "isActive": false,
                "originalPosition_x": 1856.0,
                "originalPosition_y": 501.0,
                "plataformSize_x": 1856.0,
                "plataformSize_y": 501.0,
                "plataformType": 1,
                "position_x": 1856.0,
                "position_y": 501.0,
                "regenClock": 38.04823303222656,
                "size_x": 26.5,
                "size_y": 11.5,
                "type": "Plataform",
                "velocity_x": 0.0,
                "velocity_y": 0.0
            },
            {
                "clock": 0.0,
                "isActive": false,
                "originalPosition_x": 1901.050048828125,
                "originalPosition_y": 501.0,
                "plataformSize_x": 1901.050048828125,
                "plataformSize_y": 501.0,
                "plataformType": 1,
                "position_x": 1901.050048828125,
                "position_y": 501.0,
                "regenClock": 38.04823303222656,
                "size_x": 26.5,
                "size_y": 11.5,
                "type": "Plataform",
                "velocity_x": 0.0,
                "velocity_y": 0.0
            },
            {
                "clock": 0.0,
                "isActive": false,
                "originalPosition_x": 9757.0,
                "originalPosition_y": 243.0,
                "plataformSize_x": 9757.0,
                "plataformSize_y": 243.0,
                "plataformType": 0,
                "position_x": 9757.0,
                "position_y": 243.0,
                "regenClock": 38.04823303222656,
                "size_x": 34.0,
                "size_y": 10.5,
                "type": "Plataform",
                "velocity_x": 0.0,
                "velocity_y": 0.0
            },
            {
                "clock": 0.0,
                "isActive": false,
                "originalPosition_x": 9814.7998046875,
                "originalPosition_y": 243.0,
                "plataformSize_x": 9814.7998046875,
                "plataformSize_y": 243.0,
                "plataformType": 0,
                "position_x": 9814.7998046875,
                "position_y": 243.0,
                "regenClock": 38.04823303222656,
                "size_x": 34.0,
                "size_y": 10.5,
                "type": "Plataform",
                "velocity_x": 0.0,
                "velocity_y": 0.0
            },
            {
                "clock": 0.0,
                "isActive": false,
                "originalPosition_x": 7691.0,
                "originalPosition_y": 104.0,
                "plataformSize_x": 7691.0,
                "plataformSize_y": 104.0,
                "plataformType": 0,
                "position_x": 7691.0,
                "position_y": 104.0,
                "regenClock": 38.04823303222656,
                "size_x": 34.0,
                "size_y": 10.5,
                "type": "Plataform",
                "velocity_x": 0.0,
                "velocity_y": 0.0
            },
            {
                "clock": 0.0,
                "isActive": false,
                "originalPosition_x": 7748.7998046875,
                "originalPosition_y": 104.0,
                "plataformSize_x": 7748.7998046875,
                "plataformSize_y": 104.0,
                "plataformType": 0,
                "position_x": 7748.7998046875,
                "position_y": 104.0,
                "regenClock": 38.04823303222656,
                "size_x": 34.0,
                "size_y": 10.5,
                "type": "Plataform",
                "velocity_x": 0.0,
                "velocity_y": 0.0
            },
            {
                "clock": 0.0,
                "isActive": false,
                "originalPosition_x": 11022.0,
                "originalPosition_y": 212.0,
                "plataformSize_x": 11022.0,
                "plataformSize_y": 212.0,
                "plataformType": 0,
                "position_x": 11022.0,
                "position_y": 212.0,
                "regenClock": 38.04823303222656,
                "size_x": 34.0,
                "size_y": 10.5,
                "type": "Plataform",
                "velocity_x": 0.0,
                "velocity_y": 0.0
            },
            {
                "clock": 0.0,
                "isActive": false,
                "originalPosition_x": 11079.7998046875,
                "originalPosition_y": 212.0,
                "plataformSize_x": 11079.7998046875,
                "plataformSize_y": 212.0,
                "plataformType": 0,
                "position_x": 11079.7998046875,
                "position_y": 212.0,
                "regenClock": 38.04823303222656,
                "size_x": 34.0,
                "size_y": 10.5,
                "type": "Plataform",
                "velocity_x": 0.0,
                "velocity_y": 0.0
            },
            {
                "clock": 0.0,
                "isActive": false,
                "originalPosition_x": 9353.0,
                "originalPosition_y": 524.0,
                "plataformSize_x": 9353.0,
                "plataformSize_y": 524.0,
                "plataformType": 1,
                "position_x": 9353.0,
                "position_y": 524.0,
                "regenClock": 38.04823303222656,
                "size_x": 26.5,
                "size_y": 11.5,
                "type": "Plataform",
                "velocity_x": 0.0,
                "velocity_y": 0.0
            },
            {
                "clock": 0.0,
                "isActive": false,
                "originalPosition_x": 9398.0498046875,
                "originalPosition_y": 524.0,
                "plataformSize_x": 9398.0498046875,
                "plataformSize_y": 524.0,
                "plataformType": 1,
                "position_x": 9398.0498046875,
                "position_y": 524.0,
                "regenClock": 38.04823303222656,
                "size_x": 26.5,
                "size_y": 11.5,
                "type": "Plataform",
                "velocity_x": 0.0,
                "velocity_y": 0.0
            }
        ],
        "passedPhase": false,
        "passingX": 11900.0,
        "phaseSize_x": 12000.0,
        "phaseSize_y": 850.0,
        "phaseType": "FirstPhase",
        "type": "FirstPhase"
    },
    "players": [
        {
            "aceleration": 50.0,
            "health": 15,
            "jumpForce": 15.0,
            "name": "DDE",
            "player_num": 1,
            "position_x": 4098.22412109375,
            "position_y": 770.0,
            "score": 200,
            "type": "Player1",
            "velocity_x": 0.0,
            "velocity_y": 0.0
        },
        null
    ],
    "state": 3
}